{"type":"FeatureCollection","features":[{"geometry":{"coordinates":[76.75201832482028,30.890753081223465],"type":"Point"},"id":"0","properties":{"label":3,"name":"trees"},"type":"Feature"},{"geometry":{"coordinates":[76.69012131802091,30.948990483741486],"type":"Point"},"id":"1","properties":{"label":3,"name":"trees"},"type":"Feature"},{"geometry":{"coordinates":[76.64171280972013,30.978005272979612],"type":"Point"},"id":"2","properties":{"label":3,"name":"trees"},"type":"Feature"},{"geometry":{"coordinates":[76.49754664270196,31.015478083531434],"type":"Point"},"id":"3","properties":{"label":3,"name":"trees"},"type":"Feature"},{"geometry":{"coordinates":[76.47660395471368,31.056956504138],"type":"Point"},"id":"4","properties":{"label":3,"name":"trees"},"type":"Feature"},{"geometry":{"coordinates":[76.46905085412774,31.07577762534076],"type":"Point"},"id":"5","properties":{"label":3,"name":"trees"},"type":"Feature"},{"geometry":{"coordinates":[76.416865795534,31.11291201191765],"type":"Point"},"id":"6","properties":{"label":3,"name":"trees"},"type":"Feature"},{"geometry":{"coordinates":[76.38837000695978,31.142594905245645],"type":"Point"},"id":"7","properties":{"label":3,"name":"trees"},"type":"Feature"},{"geometry":{"coordinates":[76.37669703332696,31.178352069765484],"type":"Point"},"id":"8","properties":{"label":3,"name":"trees"},"type":"Feature"},{"geometry":{"coordinates":[76.27902150048563,31.241420153023586],"type":"Point"},"id":"9","properties":{"label":3,"name":"trees"},"type":"Feature"},{"geometry":{"coordinates":[76.16666143803843,31.334451914256277],"type":"Point"},"id":"10","properties":{"label":3,"name":"trees"},"type":"Feature"},{"geometry":{"coordinates":[76.15121191411265,31.391503567191137],"type":"Point"},"id":"11","properties":{"label":3,"name":"trees"},"type":"Feature"},{"geometry":{"coordinates":[76.13507574467906,31.435160830559848],"type":"Point"},"id":"12","properties":{"label":3,"name":"trees"},"type":"Feature"},{"geometry":{"coordinates":[76.08047837469451,31.509391554910415],"type":"Point"},"id":"13","properties":{"label":3,"name":"trees"},"type":"Feature"},{"geometry":{"coordinates":[76.00975388738982,31.564988262554305],"type":"Point"},"id":"14","properties":{"label":3,"name":"trees"},"type":"Feature"},{"geometry":{"coordinates":[75.94752528271059,31.618217612698242],"type":"Point"},"id":"15","properties":{"label":3,"name":"trees"},"type":"Feature"},{"geometry":{"coordinates":[75.90577320940945,31.74389162260083],"type":"Point"},"id":"16","properties":{"label":3,"name":"trees"},"type":"Feature"},{"geometry":{"coordinates":[75.57361194535939,31.86881052890777],"type":"Point"},"id":"17","properties":{"label":3,"name":"trees"},"type":"Feature"},{"geometry":{"coordinates":[75.42450300152474,31.904536105022498],"type":"Point"},"id":"18","properties":{"label":3,"name":"trees"},"type":"Feature"},{"geometry":{"coordinates":[75.02740744520544,31.526953651555644],"type":"Point"},"id":"19","properties":{"label":3,"name":"trees"},"type":"Feature"},{"geometry":{"coordinates":[74.85222245139511,30.003234059110817],"type":"Point"},"id":"20","properties":{"label":3,"name":"trees"},"type":"Feature"},{"geometry":{"coordinates":[75.9638319179836,30.265703497927014],"type":"Point"},"id":"21","properties":{"label":3,"name":"trees"},"type":"Feature"},{"geometry":{"coordinates":[76.0586137454775,30.386439423702306],"type":"Point"},"id":"22","properties":{"label":3,"name":"trees"},"type":"Feature"},{"geometry":{"coordinates":[75.17380956319094,31.478552964912407],"type":"Point"},"id":"23","properties":{"label":3,"name":"trees"},"type":"Feature"},{"geometry":{"coordinates":[75.2296445267245,31.467684116567206],"type":"Point"},"id":"24","properties":{"label":3,"name":"trees"},"type":"Feature"},{"geometry":{"coordinates":[74.94069705872636,31.148867999601258],"type":"Point"},"id":"25","properties":{"label":3,"name":"trees"},"type":"Feature"},{"geometry":{"coordinates":[75.63369421499593,31.509174564389827],"type":"Point"},"id":"26","properties":{"label":3,"name":"trees"},"type":"Feature"},{"geometry":{"coordinates":[75.7565233832346,31.901798493950075],"type":"Point"},"id":"27","properties":{"label":3,"name":"trees"},"type":"Feature"},{"geometry":{"coordinates":[75.75643755254612,31.900486889392667],"type":"Point"},"id":"28","properties":{"label":3,"name":"trees"},"type":"Feature"},{"geometry":{"coordinates":[75.73873397950346,31.961462783985585],"type":"Point"},"id":"29","properties":{"label":3,"name":"trees"},"type":"Feature"}]}